{"_type":"export","__export_format":4,"__export_date":"2024-02-26T11:50:14.456Z","__export_source":"insomnia.desktop.app:v8.6.1","resources":[{"_id":"req_2ee0b4966b8c42c0a6c72937e24c1472","parentId":"wrk_ef16eedc21a14f40b23b9339d1707bc0","modified":1707504469353,"created":1706901278847,"url":"{{ _.url_api }}home/get_endpoints","name":"home/get_endpoints","description":"","method":"GET","body":{},"parameters":[],"headers":[{"name":"User-Agent","value":"insomnia/8.6.0"}],"authentication":{},"metaSortKey":-1706901278847,"isPrivate":false,"pathParameters":[],"settingStoreCookies":true,"settingSendCookies":true,"settingDisableRenderRequestBody":false,"settingEncodeUrl":true,"settingRebuildPath":true,"settingFollowRedirects":"global","_type":"request"},{"_id":"wrk_ef16eedc21a14f40b23b9339d1707bc0","parentId":null,"modified":1708887371622,"created":1708887371622,"name":"XSTREAMING","description":"","scope":"collection","_type":"workspace"},{"_id":"req_8cffc66b542b458e817ec0c2c53e3c99","parentId":"wrk_ef16eedc21a14f40b23b9339d1707bc0","modified":1707504483633,"created":1706904246061,"url":"{{ _.url_api }}home/highlight_large/","name":"home/highlight_large/","description":"","method":"GET","body":{},"parameters":[],"headers":[{"name":"User-Agent","value":"insomnia/8.6.0"}],"authentication":{},"metaSortKey":-1706293343103.5,"isPrivate":false,"pathParameters":[],"settingStoreCookies":true,"settingSendCookies":true,"settingDisableRenderRequestBody":false,"settingEncodeUrl":true,"settingRebuildPath":true,"settingFollowRedirects":"global","_type":"request"},{"_id":"req_ddca2e51cf404808a308a9e55c210b56","parentId":"wrk_ef16eedc21a14f40b23b9339d1707bc0","modified":1707504490501,"created":1706906058559,"url":"{{ _.url_api }}home/channels/1","name":"home/channels/1","description":"","method":"GET","body":{},"parameters":[],"headers":[{"name":"User-Agent","value":"insomnia/8.6.0"}],"authentication":{},"metaSortKey":-1705989375231.75,"isPrivate":false,"pathParameters":[],"settingStoreCookies":true,"settingSendCookies":true,"settingDisableRenderRequestBody":false,"settingEncodeUrl":true,"settingRebuildPath":true,"settingFollowRedirects":"global","_type":"request"},{"_id":"req_497992e71f78474f9d4c10cdce36e08f","parentId":"wrk_ef16eedc21a14f40b23b9339d1707bc0","modified":1707504625578,"created":1707504598004,"url":"{{ _.url_api }}home/ads_mega_banner/1","name":"home/ads_mega_banner/1","description":"","method":"GET","body":{},"parameters":[],"headers":[{"name":"User-Agent","value":"insomnia/8.6.0"}],"authentication":{},"metaSortKey":-1705932381255.7969,"isPrivate":false,"pathParameters":[],"settingStoreCookies":true,"settingSendCookies":true,"settingDisableRenderRequestBody":false,"settingEncodeUrl":true,"settingRebuildPath":true,"settingFollowRedirects":"global","_type":"request"},{"_id":"req_5b3f85273e75496889a4936354f978ea","parentId":"wrk_ef16eedc21a14f40b23b9339d1707bc0","modified":1707504635426,"created":1706907486299,"url":"{{ _.url_api }}home/live_now","name":"home/live_now","description":"","method":"GET","body":{},"parameters":[],"headers":[{"name":"User-Agent","value":"insomnia/8.6.0"}],"authentication":{},"metaSortKey":-1705922882259.8047,"isPrivate":false,"pathParameters":[],"settingStoreCookies":true,"settingSendCookies":true,"settingDisableRenderRequestBody":false,"settingEncodeUrl":true,"settingRebuildPath":true,"settingFollowRedirects":"global","_type":"request"},{"_id":"req_86733d3d67a1405ba7c262e1a388a798","parentId":"wrk_ef16eedc21a14f40b23b9339d1707bc0","modified":1707504507461,"created":1707502712629,"url":"{{ _.url_api }}home/highlight_medium","name":"home/highlight_medium","description":"","method":"GET","body":{},"parameters":[],"headers":[{"name":"User-Agent","value":"insomnia/8.6.0"}],"authentication":{},"metaSortKey":-1705913383263.8125,"isPrivate":false,"pathParameters":[],"settingStoreCookies":true,"settingSendCookies":true,"settingDisableRenderRequestBody":false,"settingEncodeUrl":true,"settingRebuildPath":true,"settingFollowRedirects":"global","_type":"request"},{"_id":"req_213e0f7e9f4c4fd3840439b0a50b4621","parentId":"wrk_ef16eedc21a14f40b23b9339d1707bc0","modified":1707504514172,"created":1707503513307,"url":"{{ _.url_api }}home/playlist","name":"home/playlist","description":"","method":"GET","body":{},"parameters":[],"headers":[{"name":"User-Agent","value":"insomnia/8.6.0"}],"authentication":{},"metaSortKey":-1705799395311.9062,"isPrivate":false,"pathParameters":[],"settingStoreCookies":true,"settingSendCookies":true,"settingDisableRenderRequestBody":false,"settingEncodeUrl":true,"settingRebuildPath":true,"settingFollowRedirects":"global","_type":"request"},{"_id":"req_0b0920d7ff8445db91c7d8b319e68ef0","parentId":"wrk_ef16eedc21a14f40b23b9339d1707bc0","modified":1708887725285,"created":1708887433490,"url":"{{ _.url_api }}home/ads_medium_banner/2","name":"home/ads_medium_banner/1","description":"","method":"GET","body":{},"parameters":[],"headers":[{"name":"User-Agent","value":"insomnia/8.6.0"}],"authentication":{},"metaSortKey":-1705770898323.9297,"isPrivate":false,"pathParameters":[],"settingStoreCookies":true,"settingSendCookies":true,"settingDisableRenderRequestBody":false,"settingEncodeUrl":true,"settingRebuildPath":true,"settingFollowRedirects":"global","_type":"request"},{"_id":"req_9e68c26d276a4198b3cefdfc6dfaa0da","parentId":"wrk_ef16eedc21a14f40b23b9339d1707bc0","modified":1708948167818,"created":1708948160944,"url":"{{ _.url_api }}home/ads_small_banner/1","name":"home/ads_small_banner/1","description":"","method":"GET","body":{},"parameters":[],"headers":[{"name":"User-Agent","value":"insomnia/8.6.0"}],"authentication":{},"metaSortKey":-1705756649829.9414,"isPrivate":false,"pathParameters":[],"settingStoreCookies":true,"settingSendCookies":true,"settingDisableRenderRequestBody":false,"settingEncodeUrl":true,"settingRebuildPath":true,"settingFollowRedirects":"global","_type":"request"},{"_id":"req_8810bb89f1214effb6af0d0608815a9d","parentId":"wrk_ef16eedc21a14f40b23b9339d1707bc0","modified":1707504530136,"created":1707503712547,"url":"{{ _.url_api }}home/upcoming_events","name":"home/upcoming_events","description":"","method":"GET","body":{},"parameters":[],"headers":[{"name":"User-Agent","value":"insomnia/8.6.0"}],"authentication":{},"metaSortKey":-1705742401335.9531,"isPrivate":false,"pathParameters":[],"settingStoreCookies":true,"settingSendCookies":true,"settingDisableRenderRequestBody":false,"settingEncodeUrl":true,"settingRebuildPath":true,"settingFollowRedirects":"global","_type":"request"},{"_id":"req_981d3cb1cd4b4af1a6f23281de4615f1","parentId":"wrk_ef16eedc21a14f40b23b9339d1707bc0","modified":1707504561179,"created":1707504548295,"url":"{{ _.url_api }}upcoming_events/get_endpoints","name":"upcoming_events/get_endpoints","description":"","method":"GET","body":{},"parameters":[],"headers":[{"name":"User-Agent","value":"insomnia/8.6.0"}],"authentication":{},"metaSortKey":-1705742401235.9531,"isPrivate":false,"pathParameters":[],"settingStoreCookies":true,"settingSendCookies":true,"settingDisableRenderRequestBody":false,"settingEncodeUrl":true,"settingRebuildPath":true,"settingFollowRedirects":"global","_type":"request"},{"_id":"req_e61c12ee11bb45afbb9dd73c6c529307","parentId":"wrk_ef16eedc21a14f40b23b9339d1707bc0","modified":1707504651121,"created":1707504645938,"url":"{{ _.url_api }}upcoming_events/live_now","name":"upcoming_events/live_now","description":"","method":"GET","body":{},"parameters":[],"headers":[{"name":"User-Agent","value":"insomnia/8.6.0"}],"authentication":{},"metaSortKey":-1705742401135.9531,"isPrivate":false,"pathParameters":[],"settingStoreCookies":true,"settingSendCookies":true,"settingDisableRenderRequestBody":false,"settingEncodeUrl":true,"settingRebuildPath":true,"settingFollowRedirects":"global","_type":"request"},{"_id":"req_513d7f8e824e497fa4ee0e79deb7d312","parentId":"wrk_ef16eedc21a14f40b23b9339d1707bc0","modified":1707507176534,"created":1707507167427,"url":"{{ _.url_api }}upcoming_events/calendar","name":"upcoming_events/calendar","description":"","method":"GET","body":{},"parameters":[],"headers":[{"name":"User-Agent","value":"insomnia/8.6.0"}],"authentication":{},"metaSortKey":-1705713904247.9766,"isPrivate":false,"pathParameters":[],"settingStoreCookies":true,"settingSendCookies":true,"settingDisableRenderRequestBody":false,"settingEncodeUrl":true,"settingRebuildPath":true,"settingFollowRedirects":"global","_type":"request"},{"_id":"req_160d3d3f026948f08bef6bb61f1e9969","parentId":"wrk_ef16eedc21a14f40b23b9339d1707bc0","modified":1707509004507,"created":1707508812106,"url":"{{ _.url_api }}channels/1/get_endpoints","name":"channels/1/get_endpoints","description":"","method":"GET","body":{},"parameters":[],"headers":[{"name":"User-Agent","value":"insomnia/8.6.0"}],"authentication":{},"metaSortKey":-1705713904147.9766,"isPrivate":false,"pathParameters":[],"settingStoreCookies":true,"settingSendCookies":true,"settingDisableRenderRequestBody":false,"settingEncodeUrl":true,"settingRebuildPath":true,"settingFollowRedirects":"global","_type":"request"},{"_id":"req_8e5614c6feec4787805a2c32b76826b6","parentId":"wrk_ef16eedc21a14f40b23b9339d1707bc0","modified":1707509136496,"created":1707509129269,"url":"{{ _.url_api }}channels/1/highlight_medium","name":"channels/1/highlight_medium","description":"","method":"GET","body":{},"parameters":[],"headers":[{"name":"User-Agent","value":"insomnia/8.6.0"}],"authentication":{},"metaSortKey":-1705699655753.9883,"isPrivate":false,"pathParameters":[],"settingStoreCookies":true,"settingSendCookies":true,"settingDisableRenderRequestBody":false,"settingEncodeUrl":true,"settingRebuildPath":true,"settingFollowRedirects":"global","_type":"request"},{"_id":"req_5561a5f0b10048b1b8e1c854042dc104","parentId":"wrk_ef16eedc21a14f40b23b9339d1707bc0","modified":1707509845636,"created":1707509841697,"url":"{{ _.url_api }}channels/1/store","name":"channels/1/store","description":"","method":"GET","body":{},"parameters":[],"headers":[{"name":"User-Agent","value":"insomnia/8.6.0"}],"authentication":{},"metaSortKey":-1705692531556.9941,"isPrivate":false,"pathParameters":[],"settingStoreCookies":true,"settingSendCookies":true,"settingDisableRenderRequestBody":false,"settingEncodeUrl":true,"settingRebuildPath":true,"settingFollowRedirects":"global","_type":"request"},{"_id":"req_09f8bea20ddd4933992aec629e3f118d","parentId":"wrk_ef16eedc21a14f40b23b9339d1707bc0","modified":1707511636412,"created":1707509958179,"url":"{{ _.url_api }}channels/1/playlist/1","name":"channels/1/playlist/1","description":"","method":"GET","body":{},"parameters":[],"headers":[{"name":"User-Agent","value":"insomnia/8.6.0"}],"authentication":{},"metaSortKey":-1705688969458.497,"isPrivate":false,"pathParameters":[],"settingStoreCookies":true,"settingSendCookies":true,"settingDisableRenderRequestBody":false,"settingEncodeUrl":true,"settingRebuildPath":true,"settingFollowRedirects":"global","_type":"request"},{"_id":"req_33e08a3111864b419e1f239cce8846c1","parentId":"wrk_ef16eedc21a14f40b23b9339d1707bc0","modified":1707511316362,"created":1707511307756,"url":"{{ _.url_api }}channels/1/ads_medium_banner/2","name":"channels/1/ads_medium_banner/1","description":"","method":"GET","body":{},"parameters":[],"headers":[{"name":"User-Agent","value":"insomnia/8.6.0"}],"authentication":{},"metaSortKey":-1705687188409.2485,"isPrivate":false,"pathParameters":[],"settingStoreCookies":true,"settingSendCookies":true,"settingDisableRenderRequestBody":false,"settingEncodeUrl":true,"settingRebuildPath":true,"settingFollowRedirects":"global","_type":"request"},{"_id":"req_087a7f977b084f748685adbc5902f8d1","parentId":"wrk_ef16eedc21a14f40b23b9339d1707bc0","modified":1707511426632,"created":1707511423649,"url":"{{ _.url_api }}channels/1/series/2","name":"channels/1/series/1","description":"","method":"GET","body":{},"parameters":[],"headers":[{"name":"User-Agent","value":"insomnia/8.6.0"}],"authentication":{},"metaSortKey":-1705686297884.6243,"isPrivate":false,"pathParameters":[],"settingStoreCookies":true,"settingSendCookies":true,"settingDisableRenderRequestBody":false,"settingEncodeUrl":true,"settingRebuildPath":true,"settingFollowRedirects":"global","_type":"request"},{"_id":"req_a834287b26f34b99bea302c2181d3c82","parentId":"wrk_ef16eedc21a14f40b23b9339d1707bc0","modified":1707511651435,"created":1707511647441,"url":"{{ _.url_api }}channels/1/playlist/1","name":"channels/1/playlist/2","description":"","method":"GET","body":{},"parameters":[],"headers":[{"name":"User-Agent","value":"insomnia/8.6.0"}],"authentication":{},"metaSortKey":-1705686297784.6243,"isPrivate":false,"pathParameters":[],"settingStoreCookies":true,"settingSendCookies":true,"settingDisableRenderRequestBody":false,"settingEncodeUrl":true,"settingRebuildPath":true,"settingFollowRedirects":"global","_type":"request"},{"_id":"req_e06625d54b1142489f036716914eab09","parentId":"wrk_ef16eedc21a14f40b23b9339d1707bc0","modified":1708114159028,"created":1708114143204,"url":"{{ _.url_api }}live_details/get_endpoints","name":"live_details/get_endpoints/","description":"","method":"GET","body":{},"parameters":[],"headers":[{"name":"User-Agent","value":"insomnia/8.6.0"}],"authentication":{},"metaSortKey":-1705479032616.601,"isPrivate":false,"pathParameters":[],"settingStoreCookies":true,"settingSendCookies":true,"settingDisableRenderRequestBody":false,"settingEncodeUrl":true,"settingRebuildPath":true,"settingFollowRedirects":"global","_type":"request"},{"_id":"req_6fadd030bd2c4e0f9940a3f33e602194","parentId":"wrk_ef16eedc21a14f40b23b9339d1707bc0","modified":1708115288899,"created":1708115283551,"url":"{{ _.url_api }}live_details/player/","name":"live_details/player/","description":"","method":"GET","body":{},"parameters":[],"headers":[{"name":"User-Agent","value":"insomnia/8.6.0"}],"authentication":{},"metaSortKey":-1705375400032.5896,"isPrivate":false,"pathParameters":[],"settingStoreCookies":true,"settingSendCookies":true,"settingDisableRenderRequestBody":false,"settingEncodeUrl":true,"settingRebuildPath":true,"settingFollowRedirects":"global","_type":"request"},{"_id":"req_7da924d892ff46aeb5f46b43b03ece04","parentId":"wrk_ef16eedc21a14f40b23b9339d1707bc0","modified":1708115306060,"created":1708115302570,"url":"{{ _.url_api }}live_details/content/","name":"live_details/content","description":"","method":"GET","body":{},"parameters":[],"headers":[{"name":"User-Agent","value":"insomnia/8.6.0"}],"authentication":{},"metaSortKey":-1705323583740.584,"isPrivate":false,"pathParameters":[],"settingStoreCookies":true,"settingSendCookies":true,"settingDisableRenderRequestBody":false,"settingEncodeUrl":true,"settingRebuildPath":true,"settingFollowRedirects":"global","_type":"request"},{"_id":"req_b5927ada87814b6eb5fc57a225f5e60a","parentId":"wrk_ef16eedc21a14f40b23b9339d1707bc0","modified":1708115322541,"created":1708115318246,"url":"{{ _.url_api }}live_details/store/","name":"live_details/store","description":"","method":"GET","body":{},"parameters":[],"headers":[{"name":"User-Agent","value":"insomnia/8.6.0"}],"authentication":{},"metaSortKey":-1705297675594.581,"isPrivate":false,"pathParameters":[],"settingStoreCookies":true,"settingSendCookies":true,"settingDisableRenderRequestBody":false,"settingEncodeUrl":true,"settingRebuildPath":true,"settingFollowRedirects":"global","_type":"request"},{"_id":"req_54faf5615f1a4747a106f97a095de0e7","parentId":"wrk_ef16eedc21a14f40b23b9339d1707bc0","modified":1708115547653,"created":1708115343453,"url":"{{ _.url_api }}live_details/ads_medium_banner/1","name":"live_details/ads_medium_banner/1","description":"","method":"GET","body":{},"parameters":[],"headers":[{"name":"User-Agent","value":"insomnia/8.6.0"}],"authentication":{},"metaSortKey":-1705284721521.5796,"isPrivate":false,"pathParameters":[],"settingStoreCookies":true,"settingSendCookies":true,"settingDisableRenderRequestBody":false,"settingEncodeUrl":true,"settingRebuildPath":true,"settingFollowRedirects":"global","_type":"request"},{"_id":"req_ca380570e13b4c23b2e090ae3b1a9884","parentId":"wrk_ef16eedc21a14f40b23b9339d1707bc0","modified":1708115460816,"created":1708115453840,"url":"{{ _.url_api }}live_details/live_now/","name":"live_details/live_now","description":"","method":"GET","body":{},"parameters":[],"headers":[{"name":"User-Agent","value":"insomnia/8.6.0"}],"authentication":{},"metaSortKey":-1705278244485.0789,"isPrivate":false,"pathParameters":[],"settingStoreCookies":true,"settingSendCookies":true,"settingDisableRenderRequestBody":false,"settingEncodeUrl":true,"settingRebuildPath":true,"settingFollowRedirects":"global","_type":"request"},{"_id":"req_eba5f0993b5f4158b83f79011a384f68","parentId":"wrk_ef16eedc21a14f40b23b9339d1707bc0","modified":1708115480472,"created":1708115474538,"url":"{{ _.url_api }}live_details/upcoming_events/","name":"live_details/upcoming_events","description":"","method":"GET","body":{},"parameters":[],"headers":[{"name":"User-Agent","value":"insomnia/8.6.0"}],"authentication":{},"metaSortKey":-1705275005966.8286,"isPrivate":false,"pathParameters":[],"settingStoreCookies":true,"settingSendCookies":true,"settingDisableRenderRequestBody":false,"settingEncodeUrl":true,"settingRebuildPath":true,"settingFollowRedirects":"global","_type":"request"},{"_id":"req_6cab35cab1db47d48ce797ca4e4c53da","parentId":"wrk_ef16eedc21a14f40b23b9339d1707bc0","modified":1708115503695,"created":1708115498447,"url":"{{ _.url_api }}live_details/celebrities","name":"live_details/celebrities","description":"","method":"GET","body":{},"parameters":[],"headers":[{"name":"User-Agent","value":"insomnia/8.6.0"}],"authentication":{},"metaSortKey":-1705273386707.7034,"isPrivate":false,"pathParameters":[],"settingStoreCookies":true,"settingSendCookies":true,"settingDisableRenderRequestBody":false,"settingEncodeUrl":true,"settingRebuildPath":true,"settingFollowRedirects":"global","_type":"request"},{"_id":"req_35c2280a5e1248258ef943aea2db5e2f","parentId":"wrk_ef16eedc21a14f40b23b9339d1707bc0","modified":1708115534621,"created":1708115526094,"url":"{{ _.url_api }}live_details/ads_medium_banner/2","name":"live_details/ads_medium_banner/2","description":"","method":"GET","body":{},"parameters":[],"headers":[{"name":"User-Agent","value":"insomnia/8.6.0"}],"authentication":{},"metaSortKey":-1705272577078.1406,"isPrivate":false,"pathParameters":[],"settingStoreCookies":true,"settingSendCookies":true,"settingDisableRenderRequestBody":false,"settingEncodeUrl":true,"settingRebuildPath":true,"settingFollowRedirects":"global","_type":"request"},{"_id":"req_76f320f2f8074f4b8191631e4e59a1c0","parentId":"wrk_ef16eedc21a14f40b23b9339d1707bc0","modified":1708115629217,"created":1708115582242,"url":"{{ _.url_api }}video_details/get_endpoints","name":"video_details/get_endpoints","description":"","method":"GET","body":{},"parameters":[],"headers":[{"name":"User-Agent","value":"insomnia/8.6.0"}],"authentication":{},"metaSortKey":-1705272172263.3594,"isPrivate":false,"pathParameters":[],"settingStoreCookies":true,"settingSendCookies":true,"settingDisableRenderRequestBody":false,"settingEncodeUrl":true,"settingRebuildPath":true,"settingFollowRedirects":"global","_type":"request"},{"_id":"req_1c32ea4dbd074414b70eccefc5fb2047","parentId":"wrk_ef16eedc21a14f40b23b9339d1707bc0","modified":1708115668931,"created":1708115664219,"url":"{{ _.url_api }}video_details/player","name":"video_details/player","description":"","method":"GET","body":{},"parameters":[],"headers":[{"name":"User-Agent","value":"insomnia/8.6.0"}],"authentication":{},"metaSortKey":-1705271969855.9688,"isPrivate":false,"pathParameters":[],"settingStoreCookies":true,"settingSendCookies":true,"settingDisableRenderRequestBody":false,"settingEncodeUrl":true,"settingRebuildPath":true,"settingFollowRedirects":"global","_type":"request"},{"_id":"req_61e786cdc5644a20801cdac172dfad04","parentId":"wrk_ef16eedc21a14f40b23b9339d1707bc0","modified":1708115682700,"created":1708115678774,"url":"{{ _.url_api }}video_details/details","name":"video_details/details","description":"","method":"GET","body":{},"parameters":[],"headers":[{"name":"User-Agent","value":"insomnia/8.6.0"}],"authentication":{},"metaSortKey":-1705271868652.2734,"isPrivate":false,"pathParameters":[],"settingStoreCookies":true,"settingSendCookies":true,"settingDisableRenderRequestBody":false,"settingEncodeUrl":true,"settingRebuildPath":true,"settingFollowRedirects":"global","_type":"request"},{"_id":"req_5cb0c54e38644461bc9486251561a19f","parentId":"wrk_ef16eedc21a14f40b23b9339d1707bc0","modified":1708115696468,"created":1708115692887,"url":"{{ _.url_api }}video_details/celebrities","name":"video_details/celebrities","description":"","method":"GET","body":{},"parameters":[],"headers":[{"name":"User-Agent","value":"insomnia/8.6.0"}],"authentication":{},"metaSortKey":-1705271818050.4258,"isPrivate":false,"pathParameters":[],"settingStoreCookies":true,"settingSendCookies":true,"settingDisableRenderRequestBody":false,"settingEncodeUrl":true,"settingRebuildPath":true,"settingFollowRedirects":"global","_type":"request"},{"_id":"req_5777a3b73d2244c4a8ce5c903466cdc0","parentId":"wrk_ef16eedc21a14f40b23b9339d1707bc0","modified":1708115712379,"created":1708115706669,"url":"{{ _.url_api }}video_details/related_videos","name":"video_details/related_videos","description":"","method":"GET","body":{},"parameters":[],"headers":[{"name":"User-Agent","value":"insomnia/8.6.0"}],"authentication":{},"metaSortKey":-1705271792749.502,"isPrivate":false,"pathParameters":[],"settingStoreCookies":true,"settingSendCookies":true,"settingDisableRenderRequestBody":false,"settingEncodeUrl":true,"settingRebuildPath":true,"settingFollowRedirects":"global","_type":"request"},{"_id":"req_dc80ee05d659428bac9a117298fa7cca","parentId":"wrk_ef16eedc21a14f40b23b9339d1707bc0","modified":1708115725785,"created":1708115721909,"url":"{{ _.url_api }}video_details/episodes","name":"video_details/episodes","description":"","method":"GET","body":{},"parameters":[],"headers":[{"name":"User-Agent","value":"insomnia/8.6.0"}],"authentication":{},"metaSortKey":-1705271780099.04,"isPrivate":false,"pathParameters":[],"settingStoreCookies":true,"settingSendCookies":true,"settingDisableRenderRequestBody":false,"settingEncodeUrl":true,"settingRebuildPath":true,"settingFollowRedirects":"global","_type":"request"},{"_id":"req_26c7c16899d94931a4a6acbd2ea8343d","parentId":"wrk_ef16eedc21a14f40b23b9339d1707bc0","modified":1708115747610,"created":1708115737072,"url":"{{ _.url_api }}video_details/ads_medium_banner/1","name":"video_details/ads_medium_banner/1","description":"","method":"GET","body":{},"parameters":[],"headers":[{"name":"User-Agent","value":"insomnia/8.6.0"}],"authentication":{},"metaSortKey":-1705271773773.809,"isPrivate":false,"pathParameters":[],"settingStoreCookies":true,"settingSendCookies":true,"settingDisableRenderRequestBody":false,"settingEncodeUrl":true,"settingRebuildPath":true,"settingFollowRedirects":"global","_type":"request"},{"_id":"req_ae219ec0d06f4fba93fa62f1a4e0c890","parentId":"wrk_ef16eedc21a14f40b23b9339d1707bc0","modified":1708115790512,"created":1708115786839,"url":"{{ _.url_api }}video_details/store","name":"video_details/store","description":"","method":"GET","body":{},"parameters":[],"headers":[{"name":"User-Agent","value":"insomnia/8.6.0"}],"authentication":{},"metaSortKey":-1705271770611.1936,"isPrivate":false,"pathParameters":[],"settingStoreCookies":true,"settingSendCookies":true,"settingDisableRenderRequestBody":false,"settingEncodeUrl":true,"settingRebuildPath":true,"settingFollowRedirects":"global","_type":"request"},{"_id":"req_905ff406f6c4482d89535fa81b450634","parentId":"wrk_ef16eedc21a14f40b23b9339d1707bc0","modified":1708115825797,"created":1708115800591,"url":"{{ _.url_api }}video_details/ads_medium_banner/2","name":"video_details/ads_medium_banner/2","description":"","method":"GET","body":{},"parameters":[],"headers":[{"name":"User-Agent","value":"insomnia/8.6.0"}],"authentication":{},"metaSortKey":-1705271769029.8857,"isPrivate":false,"pathParameters":[],"settingStoreCookies":true,"settingSendCookies":true,"settingDisableRenderRequestBody":false,"settingEncodeUrl":true,"settingRebuildPath":true,"settingFollowRedirects":"global","_type":"request"},{"_id":"req_9426913c2f354ccfb8bb08d6ff0765e6","parentId":"wrk_ef16eedc21a14f40b23b9339d1707bc0","modified":1708439003888,"created":1708375143413,"url":"{{ _.url_api }}live_menu/get_endpoints","name":"live_menu/get_endpoints","description":"","method":"GET","body":{},"parameters":[],"headers":[{"name":"User-Agent","value":"insomnia/8.6.0"}],"authentication":{},"metaSortKey":-1705271768239.232,"isPrivate":false,"pathParameters":[],"settingStoreCookies":true,"settingSendCookies":true,"settingDisableRenderRequestBody":false,"settingEncodeUrl":true,"settingRebuildPath":true,"settingFollowRedirects":"global","_type":"request"},{"_id":"req_72179d4de2e44ee78bfa0038727d3126","parentId":"wrk_ef16eedc21a14f40b23b9339d1707bc0","modified":1708439009011,"created":1708375167282,"url":"{{ _.url_api }}live_menu/player","name":"live_menu/player","description":"","method":"GET","body":{},"parameters":[],"headers":[{"name":"User-Agent","value":"insomnia/8.6.0"}],"authentication":{},"metaSortKey":-1705271767843.905,"isPrivate":false,"pathParameters":[],"settingStoreCookies":true,"settingSendCookies":true,"settingDisableRenderRequestBody":false,"settingEncodeUrl":true,"settingRebuildPath":true,"settingFollowRedirects":"global","_type":"request"},{"_id":"req_310ed2d6b0ff4f5bbd867f996e288f36","parentId":"wrk_ef16eedc21a14f40b23b9339d1707bc0","modified":1708439014275,"created":1708375199434,"url":"{{ _.url_api }}live_menu/details","name":"live_menu/details","description":"","method":"GET","body":{},"parameters":[],"headers":[{"name":"User-Agent","value":"insomnia/8.6.0"}],"authentication":{},"metaSortKey":-1705271767646.2417,"isPrivate":false,"pathParameters":[],"settingStoreCookies":true,"settingSendCookies":true,"settingDisableRenderRequestBody":false,"settingEncodeUrl":true,"settingRebuildPath":true,"settingFollowRedirects":"global","_type":"request"},{"_id":"req_bd41d85dc6b84f21ad518e3c2ab1289c","parentId":"wrk_ef16eedc21a14f40b23b9339d1707bc0","modified":1708439019611,"created":1708375221950,"url":"{{ _.url_api }}live_menu/live_now","name":"live_menu/live_now","description":"","method":"GET","body":{},"parameters":[],"headers":[{"name":"User-Agent","value":"insomnia/8.6.0"}],"authentication":{},"metaSortKey":-1705271767547.41,"isPrivate":false,"pathParameters":[],"settingStoreCookies":true,"settingSendCookies":true,"settingDisableRenderRequestBody":false,"settingEncodeUrl":true,"settingRebuildPath":true,"settingFollowRedirects":"global","_type":"request"},{"_id":"req_5d49fbb7ac584410964fc8ab9d4f259d","parentId":"wrk_ef16eedc21a14f40b23b9339d1707bc0","modified":1708439032927,"created":1708438741033,"url":"{{ _.url_api }}more_menu/get_endpoints","name":"more_menu/get_endpoints","description":"","method":"GET","body":{},"parameters":[],"headers":[{"name":"User-Agent","value":"insomnia/8.6.0"}],"authentication":{},"metaSortKey":-1705271767497.9941,"isPrivate":false,"pathParameters":[],"settingStoreCookies":true,"settingSendCookies":true,"settingDisableRenderRequestBody":false,"settingEncodeUrl":true,"settingRebuildPath":true,"settingFollowRedirects":"global","_type":"request"},{"_id":"req_c6ca37d0ea2c4a609da9fd73d80bdcc0","parentId":"wrk_ef16eedc21a14f40b23b9339d1707bc0","modified":1708459706285,"created":1708439058109,"url":"{{ _.url_api }}more_menu/information","name":"more_menu/information","description":"","method":"GET","body":{},"parameters":[],"headers":[{"name":"User-Agent","value":"insomnia/8.6.0"}],"authentication":{},"metaSortKey":-1705271767473.2861,"isPrivate":false,"pathParameters":[],"settingStoreCookies":true,"settingSendCookies":true,"settingDisableRenderRequestBody":false,"settingEncodeUrl":true,"settingRebuildPath":true,"settingFollowRedirects":"global","_type":"request"},{"_id":"req_acd7926ceb8c446787d9a1959cc09525","parentId":"wrk_ef16eedc21a14f40b23b9339d1707bc0","modified":1708459738137,"created":1708459730291,"url":"{{ _.url_api }}more_menu/list","name":"more_menu/list","description":"","method":"GET","body":{},"parameters":[],"headers":[{"name":"User-Agent","value":"insomnia/8.6.0"}],"authentication":{},"metaSortKey":-1705271767460.9321,"isPrivate":false,"pathParameters":[],"settingStoreCookies":true,"settingSendCookies":true,"settingDisableRenderRequestBody":false,"settingEncodeUrl":true,"settingRebuildPath":true,"settingFollowRedirects":"global","_type":"request"},{"_id":"req_11077dc6d3c7453d83a195c6c13d1aa9","parentId":"wrk_ef16eedc21a14f40b23b9339d1707bc0","modified":1708459753596,"created":1708459748989,"url":"{{ _.url_api }}more_menu/profile","name":"more_menu/profile","description":"","method":"GET","body":{},"parameters":[],"headers":[{"name":"User-Agent","value":"insomnia/8.6.0"}],"authentication":{},"metaSortKey":-1705271767454.7551,"isPrivate":false,"pathParameters":[],"settingStoreCookies":true,"settingSendCookies":true,"settingDisableRenderRequestBody":false,"settingEncodeUrl":true,"settingRebuildPath":true,"settingFollowRedirects":"global","_type":"request"},{"_id":"env_fd33ca1a3ce711905564f394365e57ed255318a7","parentId":"wrk_ef16eedc21a14f40b23b9339d1707bc0","modified":1708887413592,"created":1708887371624,"name":"Base Environment","data":{"url_api":"https://studioaweb.com.br/xstreaming/fake-api/"},"dataPropertyOrder":{"&":["url_api"]},"color":null,"isPrivate":false,"metaSortKey":1708887371624,"_type":"environment"},{"_id":"jar_fd33ca1a3ce711905564f394365e57ed255318a7","parentId":"wrk_ef16eedc21a14f40b23b9339d1707bc0","modified":1708887371625,"created":1708887371625,"name":"Default Jar","cookies":[],"_type":"cookie_jar"}]}