{"_type":"export","__export_format":4,"__export_date":"2024-02-05T17:48:22.719Z","__export_source":"insomnia.desktop.app:v8.6.0","resources":[{"_id":"req_8b916f0cd88a43669fb1eb1f6bb1f301","parentId":"wrk_8765a52dd197487babc158b471d18030","modified":1706902337782,"created":1706901278847,"url":"{{ _.url_api }}get_order_home","name":"get_order_home","description":"","method":"GET","body":{},"parameters":[],"headers":[{"name":"User-Agent","value":"insomnia/8.6.0"}],"authentication":{},"metaSortKey":-1706901278847,"isPrivate":false,"pathParameters":[],"settingStoreCookies":true,"settingSendCookies":true,"settingDisableRenderRequestBody":false,"settingEncodeUrl":true,"settingRebuildPath":true,"settingFollowRedirects":"global","_type":"request"},{"_id":"wrk_8765a52dd197487babc158b471d18030","parentId":null,"modified":1706901230991,"created":1706901230991,"name":"XSTREAMING","description":"","scope":"collection","_type":"workspace"},{"_id":"req_54a2a7ecbe264eb580a753ff97846f09","parentId":"wrk_8765a52dd197487babc158b471d18030","modified":1706904466024,"created":1706904246061,"url":"{{ _.url_api }}highlight_large/","name":"highlight_large","description":"","method":"GET","body":{},"parameters":[],"headers":[{"name":"User-Agent","value":"insomnia/8.6.0"}],"authentication":{},"metaSortKey":-1706293343103.5,"isPrivate":false,"pathParameters":[],"settingStoreCookies":true,"settingSendCookies":true,"settingDisableRenderRequestBody":false,"settingEncodeUrl":true,"settingRebuildPath":true,"settingFollowRedirects":"global","_type":"request"},{"_id":"req_bd208621c64448b1b5264e4c1b134e1d","parentId":"wrk_8765a52dd197487babc158b471d18030","modified":1706906463630,"created":1706906058559,"url":"{{ _.url_api }}channels/1","name":"channels/1","description":"","method":"GET","body":{},"parameters":[],"headers":[{"name":"User-Agent","value":"insomnia/8.6.0"}],"authentication":{},"metaSortKey":-1705989375231.75,"isPrivate":false,"pathParameters":[],"settingStoreCookies":true,"settingSendCookies":true,"settingDisableRenderRequestBody":false,"settingEncodeUrl":true,"settingRebuildPath":true,"settingFollowRedirects":"global","_type":"request"},{"_id":"req_e8287719898e417282d78a5821850a29","parentId":"wrk_8765a52dd197487babc158b471d18030","modified":1706907488141,"created":1706907486299,"url":"{{ _.url_api }}ads_mega_banner/1","name":"ads_mega_banner/1","description":"","method":"GET","body":{},"parameters":[],"headers":[{"name":"User-Agent","value":"insomnia/8.6.0"}],"authentication":{},"metaSortKey":-1705837391295.875,"isPrivate":false,"pathParameters":[],"settingStoreCookies":true,"settingSendCookies":true,"settingDisableRenderRequestBody":false,"settingEncodeUrl":true,"settingRebuildPath":true,"settingFollowRedirects":"global","_type":"request"},{"_id":"env_20b3063dd521a2e361c42faf127fee38337a7f10","parentId":"wrk_8765a52dd197487babc158b471d18030","modified":1706902009590,"created":1706901230995,"name":"Base Environment","data":{"url_api":"https://my-json-server.typicode.com/studioaweb/fake-api/"},"dataPropertyOrder":{"&":["url_api"]},"color":null,"isPrivate":false,"metaSortKey":1706901230995,"_type":"environment"},{"_id":"jar_20b3063dd521a2e361c42faf127fee38337a7f10","parentId":"wrk_8765a52dd197487babc158b471d18030","modified":1706901230997,"created":1706901230997,"name":"Default Jar","cookies":[],"_type":"cookie_jar"}]}